llm_watermark/README.md
llm_watermark/__init__.py
llm_watermark/assembly_models.py
llm_watermark/gen_model.py
llm_watermark/main.py
llm_watermark/llm_watermark.egg-info/SOURCES.txt
llm_watermark/llm_watermark.egg-info/dependency_links.txt
llm_watermark/llm_watermark.egg-info/requires.txt
llm_watermark/llm_watermark.egg-info/top_level.txt
llm_watermark/watermark/KGW.json
llm_watermark/watermark/SWEET.json
llm_watermark/watermark/Unigram.json
llm_watermark/watermark/__init__.py
llm_watermark/watermark/auto_config.py
llm_watermark/watermark/auto_watermark.py
llm_watermark/watermark/base.py
llm_watermark/watermark/openai_utils.py
llm_watermark/watermark/transformers_config.py
llm_watermark/watermark/utils.py
llm_watermark/watermark/kgw/__init__.py
llm_watermark/watermark/kgw/kgw.py
llm_watermark-0.1.18.dist-info/METADATA
llm_watermark-0.1.18.dist-info/WHEEL
llm_watermark-0.1.18.dist-info/top_level.txt
llm_watermark-0.1.18.dist-info/RECORD
