Metadata-Version: 2.4
Name: llm_watermark
Version: 0.1.18
Summary: easy way to use llm watermarking techniques
Author-email: Lin Li <xhaughearl@gmail.com>
Keywords: AI,ML,LLM
Requires-Python: >=3.10
Requires-Dist: accelerate>=1.11.0
Requires-Dist: google>=3.0.0
Requires-Dist: google-genai>=1.49.0
Requires-Dist: langchain>=1.0.4
Requires-Dist: langchain-community>=0.4.1
Requires-Dist: langchain-openai>=1.0.2
Requires-Dist: loguru>=0.7.3
Requires-Dist: tqdm>=4.67.1
Requires-Dist: transformers>=4.57.1
